marc_lint/__init__.py
marc_lint/cli.py
marc_lint/code_data.py
marc_lint/field_rules.py
marc_lint/linter.py
marc_lint/warning.py
marc_lint-0.0.5.dist-info/WHEEL
marc_lint-0.0.5.dist-info/entry_points.txt
marc_lint-0.0.5.dist-info/METADATA
marc_lint-0.0.5.dist-info/RECORD
