Metadata-Version: 2.3
Name: marc_lint
Version: 0.0.5
Summary: Python port of MARC::Lint with tests
Keywords: marc,marc21,library,cataloging,validation,lint
Author: Jacob Collins
Author-email: Jacob Collins <jakecollins1976@gmail.com>
License: MIT License
Classifier: Development Status :: 4 - Beta
Classifier: Intended Audience :: Developers
Classifier: Intended Audience :: Information Technology
Classifier: License :: OSI Approved :: MIT License
Classifier: Operating System :: OS Independent
Classifier: Programming Language :: Python :: 3
Classifier: Programming Language :: Python :: 3.10
Classifier: Programming Language :: Python :: 3.11
Classifier: Programming Language :: Python :: 3.12
Classifier: Programming Language :: Python :: 3.13
Classifier: Programming Language :: Python :: 3.14
Classifier: Topic :: Software Development :: Libraries :: Python Modules
Classifier: Topic :: Text Processing
Classifier: Typing :: Typed
Requires-Dist: pymarc>=5.0.0
Requires-Dist: python-stdnum>=2.1
Maintainer: Jacob Collins
Maintainer-email: Jacob Collins <jakecollins1976@gmail.com>
Requires-Python: >=3.10
Project-URL: Homepage, https://github.com/coliin8/marclint
Project-URL: Repository, https://github.com/coliin8/marclint
Project-URL: Issues, https://github.com/coliin8/marclint/issues
Project-URL: Changelog, https://github.com/coliin8/marclint/blob/main/CHANGELOG.md
